forecast/__init__.py
forecast/version.py
forecast/cli/main.py
forecast/core/__init__.py
forecast/core/exceptions.py
forecast/core/orchestrator.py
forecast/core/config/graph.py
forecast/core/config/inference.py
forecast/core/config/main.py
forecast/core/config/telemetry.py
forecast/core/config/tools.py
forecast/core/eval/bayesian.py
forecast/core/eval/definitions.py
forecast/core/memory/graph.py
forecast/core/schemas/__init__.py
forecast/core/schemas/base.py
forecast/core/schemas/forecast.py
forecast/core/schemas/graph.py
forecast/core/telemetry/__init__.py
forecast/core/telemetry/audit.py
forecast/core/telemetry/hashing.py
forecast/core/telemetry/manager.py
forecast/core/telemetry/schemas.py
forecast/core/telemetry/token_stream.py
forecast/core/tools/base.py
forecast/core/tools/registry.py
forecast/core/utils/__init__.py
forecast/core/utils/bundling.py
forecast/core/utils/control.py
forecast/core/utils/json_util.py
forecast/core/utils/parser.py
forecast/core/utils/privacy.py
forecast/core/utils/rate_limiter.py
forecast/core/utils/state_ops.py
forecast/kit/__init__.py
forecast/kit/patterns.py
forecast/kit/scenarios.py
forecast/kit/agents/__init__.py
forecast/kit/agents/base.py
forecast/kit/agents/graph.py
forecast/kit/agents/llm.py
forecast/kit/agents/registry.py
forecast/kit/agents/routing.py
forecast/kit/agents/tool.py
forecast/kit/agents/specialists/__init__.py
forecast/kit/agents/specialists/adversary.py
forecast/kit/agents/specialists/analyst.py
forecast/kit/assistants/main.py
forecast/kit/cognition/confidence.py
forecast/kit/eval/__init__.py
forecast/kit/eval/analytics.py
forecast/kit/eval/backtester.py
forecast/kit/eval/metrics.py
forecast/kit/eval/replayer.py
forecast/kit/eval/runner.py
forecast/kit/eval/viz.py
forecast/kit/memory/__init__.py
forecast/kit/memory/base.py
forecast/kit/memory/chroma.py
forecast/kit/memory/learner.py
forecast/kit/memory/unified.py
forecast/kit/pipelines/__init__.py
forecast/kit/pipelines/analyst.py
xrtm_forecast-0.2.2.dist-info/licenses/LICENSE
xrtm_forecast-0.2.2.dist-info/METADATA
xrtm_forecast-0.2.2.dist-info/WHEEL
xrtm_forecast-0.2.2.dist-info/entry_points.txt
xrtm_forecast-0.2.2.dist-info/top_level.txt
xrtm_forecast-0.2.2.dist-info/RECORD
