Metadata-Version: 2.4
Name: xrtm-forecast
Version: 0.2.2
Summary: Institutional-grade modular engine for generative forecasting and agentic reasoning.
Author-email: XRTM Team <moy@xrtm.org>
License: Apache-2.0
Project-URL: Repository, https://github.com/xrtm-org/forecast
Project-URL: Issues, https://github.com/xrtm-org/forecast/issues
Requires-Python: >=3.11
License-File: LICENSE
Requires-Dist: pydantic>=2.0.0
Requires-Dist: pydantic-settings>=2.0.0
Requires-Dist: aiohttp>=3.9.0
Requires-Dist: rich>=13.0.0
Requires-Dist: freezegun>=1.2.0
Requires-Dist: click>=8.0.0
Requires-Dist: google-genai>=0.1.0
Requires-Dist: openai>=1.0.0
Requires-Dist: anthropic>=0.1.0
Requires-Dist: chromadb>=0.4.0
Requires-Dist: redis>=5.0.0
Requires-Dist: pandas>=2.0.0
Requires-Dist: numpy>=1.24.0
Requires-Dist: sqlalchemy>=2.0.0
Requires-Dist: matplotlib>=3.7.0
Requires-Dist: seaborn>=0.12.0
Provides-Extra: transformers
Requires-Dist: torch>=2.0.0; extra == "transformers"
Requires-Dist: transformers>=4.40.0; extra == "transformers"
Requires-Dist: accelerate>=0.26.0; extra == "transformers"
Requires-Dist: bitsandbytes>=0.41.0; extra == "transformers"
Requires-Dist: sentencepiece>=0.2.0; extra == "transformers"
Provides-Extra: vllm
Requires-Dist: vllm>=0.3.0; extra == "vllm"
Provides-Extra: llama-cpp
Requires-Dist: llama-cpp-python>=0.2.0; extra == "llama-cpp"
Provides-Extra: xlm
Requires-Dist: transformers>=4.40.0; extra == "xlm"
Requires-Dist: torch>=2.0.0; extra == "xlm"
Provides-Extra: dev
Requires-Dist: pytest>=7.0.0; extra == "dev"
Requires-Dist: pytest-asyncio>=0.21.0; extra == "dev"
Requires-Dist: pytest-cov>=4.1.0; extra == "dev"
Requires-Dist: ruff>=0.1.0; extra == "dev"
Requires-Dist: mypy>=1.0.0; extra == "dev"
Requires-Dist: mkdocs>=1.5.0; extra == "dev"
Requires-Dist: mkdocs-material>=9.4.0; extra == "dev"
Requires-Dist: mkdocstrings[python]>=0.23.0; extra == "dev"
Dynamic: license-file
